termchart/__init__.py
termchart/termchart.py
termchart-0.0.4.dist-info/METADATA
termchart-0.0.4.dist-info/RECORD
termchart-0.0.4.dist-info/WHEEL
termchart-0.0.4.dist-info/top_level.txt
