Metadata-Version: 2.1
Name: termchart
Version: 0.0.4
Summary: A tool to draw ascii line chart in terminal
Home-page: https://github.com/Tazeg/termchart
Author: @JeffProd
Author-email: termchart@jeffprod.com
License: UNKNOWN
Project-URL: Funding, https://en.jeffprod.com/donate/
Project-URL: Twitter, https://twitter.com/jeffprod
Project-URL: Web, https://jeffprod.com
Keywords: terminal line chart graph
Platform: UNKNOWN
Classifier: Programming Language :: Python :: 3
Classifier: License :: OSI Approved :: MIT License
Classifier: Operating System :: OS Independent
